billm-0.1.6.dist-info/METADATA
billm-0.1.6.dist-info/WHEEL
billm-0.1.6.dist-info/licenses/LICENSE
billm/__init__.py
billm/config.py
billm/configuration_openelm.py
billm/modeling_llama.py
billm/modeling_mistral.py
billm/modeling_openelm.py
billm/modeling_qwen2.py
billm-0.1.6.dist-info/RECORD
