Metadata-Version: 2.1
Name: BiLLM
Version: 0.1.6
Summary: Tool for converting LLMs from uni-directional to bi-directional for tasks like classification and sentence embeddings.
Author-Email: Sean Lee <xmlee97@gmail.com>
License: MIT
Requires-Python: >=3.8
Requires-Dist: transformers>=4.41.1
